cloud_queue_worker/__init__.py
cloud_queue_worker/errors.py
cloud_queue_worker/logging.py
cloud_queue_worker/orchestrator.py
cloud_queue_worker/queue_worker.py
cloud_queue_worker/utils.py
cloud_queue_worker/validators.py
cloud_queue_worker/worker/__init__.py
cloud_queue_worker/worker/enums.py
cloud_queue_worker/worker/errors.py
cloud_queue_worker/worker/worker.py
tests/__init__.py
tests/test_orchestrator.py
tests/test_queue_worker.py
tests/test_utils.py
tests/test_worker.py
cloud_queue_worker-0.0.13.dist-info/LICENCE.md
cloud_queue_worker-0.0.13.dist-info/METADATA
cloud_queue_worker-0.0.13.dist-info/WHEEL
cloud_queue_worker-0.0.13.dist-info/top_level.txt
cloud_queue_worker-0.0.13.dist-info/RECORD
